pygrey/__init__.py
pygrey/gm.py
pygrey/gm_v2.py
pygrey/gra.py
pygrey/__pycache__/__init__.cpython-39.pyc
pygrey/__pycache__/gm.cpython-39.pyc
pygrey/__pycache__/gm_v2.cpython-39.pyc
pygrey/__pycache__/gra.cpython-39.pyc
pygrey-0.0.1a1.dist-info/LICENSE
pygrey-0.0.1a1.dist-info/METADATA
pygrey-0.0.1a1.dist-info/WHEEL
pygrey-0.0.1a1.dist-info/top_level.txt
pygrey-0.0.1a1.dist-info/RECORD
